nsight/__init__.py
nsight/analyze.py
nsight/annotation.py
nsight/exceptions.py
nsight/extraction.py
nsight/thermovision.py
nsight/transformation.py
nsight/utils.py
nsight/visualization.py
nsight/collection/__init__.py
nsight/collection/core.py
nsight/collection/ncu.py
nsight_python-0.9.5.dist-info/METADATA
nsight_python-0.9.5.dist-info/WHEEL
nsight_python-0.9.5.dist-info/licenses/LICENSE
nsight_python-0.9.5.dist-info/RECORD
