Metadata-Version: 2.4
Name: nsight-python
Version: 0.9.5
Summary: Python GPU kernel profiling interface
Project-URL: Repository, https://github.com/NVIDIA/nsight-python
Project-URL: License, https://docs.nvidia.com/nsight-python/license.html
Author-email: NVIDIA Corporation <nsight-compute-python@nvidia.com>
License: 
License-File: LICENSE
Classifier: Development Status :: 4 - Beta
Classifier: Environment :: GPU :: NVIDIA CUDA
Classifier: Intended Audience :: Developers
Classifier: License :: OSI Approved :: Apache Software License
Classifier: Programming Language :: Python
Classifier: Programming Language :: Python :: 3.10
Classifier: Programming Language :: Python :: 3.11
Classifier: Programming Language :: Python :: 3.12
Classifier: Programming Language :: Python :: 3.13
Requires-Python: >=3.10
Requires-Dist: matplotlib
Requires-Dist: ncu-report
Requires-Dist: numpy
Requires-Dist: nvidia-ml-py
Requires-Dist: nvtx
Requires-Dist: pandas
Provides-Extra: cu12
Requires-Dist: cuda-core[cu12]; extra == 'cu12'
Provides-Extra: cu13
Requires-Dist: cuda-core[cu13]; extra == 'cu13'
